{"kind":"APIResourceList","apiVersion":"v1","groupVersion":"rbac.maistra.io/v1","resources":[{"name":"servicemeshrbacconfigs","singularName":"servicemeshrbacconfig","namespaced":true,"group":"rbac.maistra.io","version":"v1","kind":"ServiceMeshRbacConfig","verbs":["delete","deletecollection","get","list","patch","create","update","watch"],"categories":["istio-io","rbac-istio-io"]},{"name":"servicemeshrbacconfigs/status","singularName":"servicemeshrbacconfig","namespaced":true,"group":"rbac.maistra.io","version":"v1","kind":"ServiceMeshRbacConfig","verbs":["get","patch","update"]}]}
